augaudio/__init__.py
augaudio/cli.py
augaudio-1.0.4.dist-info/LICENSE
augaudio-1.0.4.dist-info/METADATA
augaudio-1.0.4.dist-info/WHEEL
augaudio-1.0.4.dist-info/entry_points.txt
augaudio-1.0.4.dist-info/top_level.txt
augaudio-1.0.4.dist-info/RECORD
