Metadata-Version: 2.1
Name: augaudio
Version: 1.0.4
Summary: A simple audio data augmentation package
Home-page: https://basti564.github.io
Author: Bastian Schwickert
Author-email: Bastian.Schwickert@gmail.com
License: Apache
Project-URL: Bug Tracker, https://github.com/Basti564/augaudio/issues
Project-URL: Source Code, https://github.com/Basti564/augaudio
Platform: UNKNOWN
Classifier: License :: OSI Approved :: Apache Software License
Classifier: Programming Language :: Python :: 3
Classifier: Operating System :: OS Independent
Classifier: Topic :: Scientific/Engineering
Requires-Dist: numpy (>=1.16.2)
Requires-Dist: librosa (>=0.7.2)
Requires-Dist: numba (<0.50)
